blivomdeler_api/__init__.py
blivomdeler_api/api.py
blivomdeler_api/delivery.py
blivomdeler_api/distributor_info.py
blivomdeler_api/exceptions.py
blivomdeler_api/giftshop_item.py
blivomdeler_api/links.py
blivomdeler_api/login_result.py
blivomdeler_api/route.py
blivomdeler_api/translation.py
blivomdeler_api-0.3.0.dist-info/LICENSE
blivomdeler_api-0.3.0.dist-info/METADATA
blivomdeler_api-0.3.0.dist-info/WHEEL
blivomdeler_api-0.3.0.dist-info/top_level.txt
blivomdeler_api-0.3.0.dist-info/RECORD
