Metadata-Version: 2.1
Name: blivomdeler-api
Version: 0.3.0
Summary: A python library for doing all sorts of things on the https://blivomdeler.nu site.
Home-page: https://github.com/objectiveSquid/blivomdeler-api
Author: Magnus Zahle
Author-email: objectivesquid@outlook.com
License: MIT
Keywords: python,api,api-wrapper,blivomdeler,website-api
Classifier: Development Status :: 5 - Production/Stable
Classifier: Intended Audience :: Developers
Classifier: License :: OSI Approved :: MIT License
Classifier: Programming Language :: Python :: 3 :: Only
Classifier: Natural Language :: English
Classifier: Natural Language :: Danish
License-File: LICENSE
Requires-Dist: requests
Requires-Dist: bs4
